unblob-25.5.26.dist-info/METADATA
unblob-25.5.26.dist-info/WHEEL
unblob-25.5.26.dist-info/entry_points.txt
unblob-25.5.26.dist-info/licenses/LICENSE
unblob/__init__.py
unblob/_rust.abi3.so
unblob/_rust/__init__.pyi
unblob/_rust/math_tools.pyi
unblob/_rust/sandbox.pyi
unblob/cli.py
unblob/cli_options.py
unblob/dependencies.py
unblob/doc.py
unblob/extractor.py
unblob/extractors/README.md
unblob/extractors/__init__.py
unblob/extractors/command.py
unblob/file_utils.py
unblob/finder.py
unblob/handlers/__init__.py
unblob/handlers/archive/__init__.py
unblob/handlers/archive/_safe_tarfile.py
unblob/handlers/archive/ar.py
unblob/handlers/archive/arc.py
unblob/handlers/archive/arj.py
unblob/handlers/archive/autel/ecc.py
unblob/handlers/archive/cab.py
unblob/handlers/archive/cpio.py
unblob/handlers/archive/dlink/encrpted_img.py
unblob/handlers/archive/dlink/shrs.py
unblob/handlers/archive/dmg.py
unblob/handlers/archive/engeniustech/engenius.py
unblob/handlers/archive/hp/bdl.py
unblob/handlers/archive/hp/ipkg.py
unblob/handlers/archive/instar/bneg.py
unblob/handlers/archive/instar/instar_hd.py
unblob/handlers/archive/netgear/chk.py
unblob/handlers/archive/netgear/trx.py
unblob/handlers/archive/partclone.py
unblob/handlers/archive/qnap/qnap_nas.py
unblob/handlers/archive/rar.py
unblob/handlers/archive/sevenzip.py
unblob/handlers/archive/stuffit.py
unblob/handlers/archive/tar.py
unblob/handlers/archive/xiaomi/hdr.py
unblob/handlers/archive/zip.py
unblob/handlers/compression/__init__.py
unblob/handlers/compression/_gzip_reader.py
unblob/handlers/compression/bzip2.py
unblob/handlers/compression/compress.py
unblob/handlers/compression/gzip.py
unblob/handlers/compression/lz4.py
unblob/handlers/compression/lzh.py
unblob/handlers/compression/lzip.py
unblob/handlers/compression/lzma.py
unblob/handlers/compression/lzo.py
unblob/handlers/compression/uzip.py
unblob/handlers/compression/xz.py
unblob/handlers/compression/zlib.py
unblob/handlers/compression/zstd.py
unblob/handlers/executable/__init__.py
unblob/handlers/executable/elf.py
unblob/handlers/filesystem/__init__.py
unblob/handlers/filesystem/android/__init__.py
unblob-25.5.26.dist-info/RECORD
